pyxevil/__init__.py
pyxevil/__version__.py
pyxevil/pyxevil.py
pyxevil-1.0.2.dist-info/METADATA
pyxevil-1.0.2.dist-info/WHEEL
pyxevil-1.0.2.dist-info/top_level.txt
pyxevil-1.0.2.dist-info/RECORD
